README.md
setup.cfg
setup.py
./info.py
./setup.py
./tests/test_maxentropy.py
maxentropy/__init__.py
maxentropy/base.py
maxentropy/skmaxent.py
maxentropy/utils.py
maxentropy.egg-info/PKG-INFO
maxentropy.egg-info/SOURCES.txt
maxentropy.egg-info/dependency_links.txt
maxentropy.egg-info/requires.txt
maxentropy.egg-info/top_level.txt
maxentropy/scipy/__init__.py
maxentropy/scipy/basemodel.py
maxentropy/scipy/bigmodel.py
maxentropy/scipy/conditionalmodel.py
maxentropy/scipy/maxentutils.py
maxentropy/scipy/model.py
maxentropy/scipy/utils.py