Metadata-Version: 2.1
Name: maxentropy
Version: 0.3.0
Summary: Maximum entropy and minimum divergence models in Python
Home-page: https://github.com/PythonCharmers/maxentropy.git
Author: Ed Schofield
Author-email: ed@pythoncharmers.com
License: BSD
Keywords: maximum-entropy minimum-divergence kullback-leibler-divergence KL-divergence bayesian-inference bayes scikit-learn sklearn prior prior-distribution
Platform: UNKNOWN
Classifier: Development Status :: 4 - Beta
Classifier: Intended Audience :: Developers
Classifier: Intended Audience :: Science/Research
Classifier: License :: OSI Approved :: BSD License
Classifier: Operating System :: Microsoft :: Windows
Classifier: Operating System :: POSIX
Classifier: Operating System :: Unix
Classifier: Operating System :: MacOS
Classifier: Programming Language :: Python :: 3
Classifier: Programming Language :: Python :: 3.5
Classifier: Programming Language :: Python :: 3.6
Classifier: Programming Language :: Python :: 3.7
Classifier: Topic :: Software Development
Classifier: Topic :: Scientific/Engineering
Requires-Python: >=3.3
